jsonproto/__init__.py
jsonproto/jsonproto.py
test/__init__.py
test/sanity_test.py
jsonproto-0.0.3.dist-info/LICENSE
jsonproto-0.0.3.dist-info/METADATA
jsonproto-0.0.3.dist-info/WHEEL
jsonproto-0.0.3.dist-info/entry_points.txt
jsonproto-0.0.3.dist-info/top_level.txt
jsonproto-0.0.3.dist-info/RECORD
