Metadata-Version: 2.1
Name: jsonproto
Version: 0.0.3
Summary: Convert json payloads into protobuf messages
Author-email: Jimmy Wahlberg <jimmy.wahlberg@gmail.com>
License: MIT License
Project-URL: Homepage, https://github.com/jimbao/jsonproto
Requires-Python: >=3.8
License-File: LICENSE
Requires-Dist: protobuf
Provides-Extra: dev
Requires-Dist: pytest ; extra == 'dev'
Requires-Dist: tox ; extra == 'dev'
Requires-Dist: ruff ; extra == 'dev'
